{
  "schema_version": 1,
  "env_config": {
    "width": 50,
    "height": 50,
    "max_steps": 150,
    "n_agents": 2,
    "tiles_path": "data/tiles.json",
    "profiles_path": "data/agent_profiles.json",
    "races_path": "data/agent_races.json",
    "classes_path": "data/agent_classes.json",
    "items_path": "data/items.json",
    "monsters_path": "data/monsters.json",
    "monster_spawns_path": "data/monster_spawns.json",
    "mapgen_config_path": "data/mapgen_config.json",
    "agent_observation_config": {},
    "agent_profile_map": {},
    "agent_race_map": {},
    "agent_class_map": {},
    "monster_sight_range": 7,
    "new_tile_seen_reward": 0.02,
    "frontier_step_reward": 0.008,
    "stagnation_penalty": 0.01,
    "stagnation_threshold_steps": 10,
    "repeat_visit_penalty": 0.006,
    "repeat_visit_window": 6,
    "move_bias_reward": 0.002,
    "wait_no_enemy_penalty": 0.01,
    "wait_safe_hunger_ratio": 0.5,
    "first_enemy_seen_bonus": 0.7,
    "enemy_visible_reward": 0.01,
    "enemy_distance_delta_reward_scale": 0.01,
    "enemy_distance_delta_clip": 2.0,
    "lost_enemy_penalty": 0.01,
    "timeout_tie_penalty": 0.2,
    "engagement_bonus": 0.15,
    "render_enabled": true
  }
}
